ayaka/__init__.py
ayaka/__main__.py
ayaka/ayaka.py
ayaka/lib.py
ayaka/main.py
ayaka_kemono-1.0.0.dist-info/LICENSE.txt
ayaka_kemono-1.0.0.dist-info/METADATA
ayaka_kemono-1.0.0.dist-info/WHEEL
ayaka_kemono-1.0.0.dist-info/entry_points.txt
ayaka_kemono-1.0.0.dist-info/top_level.txt
ayaka_kemono-1.0.0.dist-info/RECORD
